invoke/__init__.py
invoke/__main__.py
invoke/_version.py
invoke/collection.py
invoke/config.py
invoke/context.py
invoke/env.py
invoke/exceptions.py
invoke/executor.py
invoke/loader.py
invoke/main.py
invoke/program.py
invoke/runners.py
invoke/tasks.py
invoke/terminals.py
invoke/util.py
invoke/watchers.py
invoke/completion/__init__.py
invoke/completion/bash.completion
invoke/completion/complete.py
invoke/completion/fish.completion
invoke/completion/zsh.completion
invoke/parser/__init__.py
invoke/parser/argument.py
invoke/parser/context.py
invoke/parser/parser.py
invoke/vendor/__init__.py
invoke/vendor/decorator.py
invoke/vendor/fluidity/__init__.py
invoke/vendor/fluidity/backwardscompat.py
invoke/vendor/fluidity/machine.py
invoke/vendor/lexicon/__init__.py
invoke/vendor/lexicon/_version.py
invoke/vendor/lexicon/alias_dict.py
invoke/vendor/lexicon/attribute_dict.py
invoke/vendor/yaml/__init__.py
invoke/vendor/yaml/composer.py
invoke/vendor/yaml/constructor.py
invoke/vendor/yaml/cyaml.py
invoke/vendor/yaml/dumper.py
invoke/vendor/yaml/emitter.py
invoke/vendor/yaml/error.py
invoke/vendor/yaml/events.py
invoke/vendor/yaml/loader.py
invoke/vendor/yaml/nodes.py
invoke/vendor/yaml/parser.py
invoke/vendor/yaml/reader.py
invoke/vendor/yaml/representer.py
invoke/vendor/yaml/resolver.py
invoke/vendor/yaml/scanner.py
invoke/vendor/yaml/serializer.py
invoke/vendor/yaml/tokens.py
neoxelox_invoke-2.0.1.dist-info/LICENSE
neoxelox_invoke-2.0.1.dist-info/METADATA
neoxelox_invoke-2.0.1.dist-info/WHEEL
neoxelox_invoke-2.0.1.dist-info/entry_points.txt
neoxelox_invoke-2.0.1.dist-info/top_level.txt
neoxelox_invoke-2.0.1.dist-info/RECORD
