Metadata-Version: 2.1
Name: neoxelox-invoke
Version: 2.0.1
Summary: (Fork) Pythonic task execution
Home-page: https://pyinvoke.org
Author: Jeff Forcier
Author-email: jeff@bitprophet.org
License: BSD
Project-URL: Docs, https://docs.pyinvoke.org
Project-URL: Source, https://github.com/pyinvoke/invoke
Project-URL: Issues, https://github.com/pyinvoke/invoke/issues
Project-URL: Changelog, https://www.pyinvoke.org/changelog.html
Project-URL: CI, https://app.circleci.com/pipelines/github/pyinvoke/invoke
Classifier: Development Status :: 5 - Production/Stable
Classifier: Environment :: Console
Classifier: Intended Audience :: Developers
Classifier: Intended Audience :: System Administrators
Classifier: License :: OSI Approved :: BSD License
Classifier: Operating System :: POSIX
Classifier: Operating System :: Unix
Classifier: Operating System :: MacOS :: MacOS X
Classifier: Operating System :: Microsoft :: Windows
Classifier: Programming Language :: Python
Classifier: Programming Language :: Python :: 3
Classifier: Programming Language :: Python :: 3.6
Classifier: Programming Language :: Python :: 3.7
Classifier: Programming Language :: Python :: 3.8
Classifier: Programming Language :: Python :: 3.9
Classifier: Programming Language :: Python :: 3.10
Classifier: Programming Language :: Python :: 3.11
Classifier: Topic :: Software Development
Classifier: Topic :: Software Development :: Build Tools
Classifier: Topic :: Software Development :: Libraries
Classifier: Topic :: Software Development :: Libraries :: Python Modules
Classifier: Topic :: System :: Software Distribution
Classifier: Topic :: System :: Systems Administration
Requires-Python: >=3.6
License-File: LICENSE
